invoiced/__init__.py
invoiced/client.py
invoiced/errors.py
invoiced/objects.py
invoiced/operations.py
invoiced/util.py
invoiced/version.py
invoiced/test/__init__.py
invoiced/test/test_client.py
invoiced/test/test_error.py
invoiced/test/test_util.py
invoiced-1.2.0.dist-info/LICENSE
invoiced-1.2.0.dist-info/METADATA
invoiced-1.2.0.dist-info/WHEEL
invoiced-1.2.0.dist-info/top_level.txt
invoiced-1.2.0.dist-info/RECORD
