Metadata-Version: 2.1
Name: invoiced
Version: 1.2.0
Summary: Invoiced client library
Home-page: https://github.com/invoiced/invoiced-python
Author: Invoiced
Author-email: support@invoiced.com
License: UNKNOWN
Platform: UNKNOWN
Classifier: Development Status :: 5 - Production/Stable
Classifier: Intended Audience :: Developers
Classifier: License :: OSI Approved :: MIT License
Classifier: Operating System :: OS Independent
Classifier: Programming Language :: Python
Classifier: Programming Language :: Python :: 3
Classifier: Programming Language :: Python :: 3.4
Classifier: Programming Language :: Python :: 3.5
Classifier: Programming Language :: Python :: 3.6
Classifier: Programming Language :: Python :: 3.7
Classifier: Programming Language :: Python :: 3.8
Classifier: Topic :: Software Development :: Libraries :: Python Modules
Requires-Dist: requests (>=2.0.0)
Requires-Dist: inflection (==0.3.1)
Provides-Extra: requests
Requires-Dist: security (>=2.0.0) ; extra == 'requests'
